{
  "title": "Holly by Stephen King - spoiler free review",
  "link": "https://www.youtube.com/watch?v=Fo3HdhjiKWQ",
  "published": "2023-09-11T16:00:10+00:00",
  "summary": "Find links to every where you can connect with me here: https://linktr.ee/criminolly\n_____\nBuy Holly from my bookshop to support the channel and indie bookstores\nUK: https://uk.bookshop.org/a/10539/9781399712910\nUS: https://bookshop.org/a/84048/9781668016138 \n__________\nBook details/Content warnings:\nTitle: Holly | Author: Stephen King | Publisher: Hodder & Stoughton | Pages: 438 | Publication date: 5th September 2023 | ISBN: 9781399712910 | Source: Purchased\nContent Warnings: Cannibalism, racism, alcoholism\n___________\nOther ways to support the channel (if you want to, honestly, just you watching my videos is amazing):\n- Join my Patreon community to support the channel and get additional perks https://www.patreon.com/user?u=86122686\n- Join my Discord community to chat books and stuff: https://discord.gg/9Whbt5KtRu\n- Visit my bookshop and support me and indie bookstores\nUK: https://uk.bookshop.org/shop/criminolly\nUS: https://bookshop.org/shop/CriminOlly\n- Check out my Amazon wish list: https://www.amazon.co.uk/hz/wishlist/ls/LKEP6NQ9BKK7?ref_=wl_share\n- Mail me things:\nOlly Clarke \nPO Box 2225\nSHOREHAM-BY-SEA\nBN43 9GT\nUnited Kingdom\n- Shop for CriminOlly merch: https://criminolly.creator-spring.com/\n________\nMusic: Who's Afraid of Halloween by Alfred Grupstra from Pixabay",
  "source_id": "5a4c45c3bafe425caee4c78828d26291",
  "feed_hash": "aa80b48b51ebf7c22b6e461fbd6c4fbe"
}